{
  "image": "https://phashion.moe/images/CAST-Legs/Rowlock-Legs.png",
  "title": "Rowlock Legs",
  "gender": {
    "female": false,
    "male": true
  },
  "race": {
    "humanoid": false,
    "cast": false
  },
  "category": "CAST Legs",
  "collection": {
    "id": "virtualstars",
    "type": "AC Scratch Ticket",
    "title": "Virtual Stars",
    "image": "https://phashion.moe/images/Collections/AC-Scratch-Ticket/virtualstars.jpg",
    "url": "https://pso2.com/news/scratch-tickets/virtualstars"
  }
}