{
  "id": "funjune2020part1",
  "type": "FUN Scratch Ticket",
  "title": "June 2020 - Part 1",
  "image": "https://phashion.moe/images/Collections/FUN-Scratch-Ticket/funjune2020part1.jpg",
  "url": "https://pso2.com/news/scratch-tickets/funjune2020part1",
  "items": [
    {
      "image": "https://phashion.moe/images/Hairstyles/Straight-Updo.png",
      "title": "Straight Updo",
      "category": "Hairstyles"
    },
    {
      "image": "https://phashion.moe/images/Hairstyles/Tied-Long-Hair.png",
      "title": "Tied Long Hair",
      "category": "Hairstyles"
    },
    {
      "image": "https://phashion.moe/images/Eyebrows/Hot-Blooded-Eyebrows.png",
      "title": "Hot-Blooded Eyebrows",
      "category": "Eyebrows"
    },
    {
      "image": "https://phashion.moe/images/Eyelashes/Anime-Eyelashes-Set.png",
      "title": "Anime Eyelashes Set",
      "category": "Eyelashes"
    },
    {
      "image": "https://phashion.moe/images/Body-Paint/Stockings-Set.png",
      "title": "Stockings Set",
      "category": "Body Paint"
    },
    {
      "image": "https://phashion.moe/images/Accessories/Ammo-Belt.png",
      "title": "Ammo Belt",
      "category": "Accessories"
    },
    {
      "image": "https://phashion.moe/images/Accessories/Ammo-Belt-B.png",
      "title": "Ammo Belt B",
      "category": "Accessories"
    },
    {
      "image": "https://phashion.moe/images/Accessories/Leg-Ammo-Belt.png",
      "title": "Leg Ammo Belt",
      "category": "Accessories"
    },
    {
      "image": "https://phashion.moe/images/Accessories/Camo-Mask-Green.png",
      "title": "Camo Mask: Green",
      "category": "Accessories"
    },
    {
      "image": "https://phashion.moe/images/Accessories/Camo-Mask-Blue.png",
      "title": "Camo Mask: Blue",
      "category": "Accessories"
    },
    {
      "image": "https://phashion.moe/images/Accessories/Camo-Mask-White.png",
      "title": "Camo Mask: White",
      "category": "Accessories"
    },
    {
      "image": "https://phashion.moe/images/Accessories/Tri-Barrel-Photon-Guns-A.png",
      "title": "Tri-Barrel Photon Guns A",
      "category": "Accessories"
    },
    {
      "image": "https://phashion.moe/images/Accessories/Tri-Barrel-Photon-Guns-B.png",
      "title": "Tri-Barrel Photon Guns B",
      "category": "Accessories"
    },
    {
      "image": "https://phashion.moe/images/Accessories/Tri-Barrel-Photon-Guns-C.png",
      "title": "Tri-Barrel Photon Guns C",
      "category": "Accessories"
    },
    {
      "image": "https://phashion.moe/images/Accessories/Stars-Headband-Pink.png",
      "title": "Stars Headband: Pink",
      "category": "Accessories"
    },
    {
      "image": "https://phashion.moe/images/Accessories/Stars-Headband-Blue.png",
      "title": "Stars Headband: Blue",
      "category": "Accessories"
    },
    {
      "image": "https://phashion.moe/images/Accessories/Stars-Headband-Yellow.png",
      "title": "Stars Headband: Yellow",
      "category": "Accessories"
    },
    {
      "image": "https://phashion.moe/images/Accessories/Stars-Headband-Green.png",
      "title": "Stars Headband: Green",
      "category": "Accessories"
    },
    {
      "image": "https://phashion.moe/images/Stickers/Taulia-Sticker.png",
      "title": "Taulia Sticker",
      "category": "Stickers"
    },
    {
      "image": "https://phashion.moe/images/Stickers/Fleet-Emblem.png",
      "title": "Fleet Emblem",
      "category": "Stickers"
    },
    {
      "image": "https://phashion.moe/images/Stickers/Marine-Emblem.png",
      "title": "Marine Emblem",
      "category": "Stickers"
    },
    {
      "image": "https://phashion.moe/images/Makeup/White-Makeup.png",
      "title": "White Makeup",
      "category": "Makeup"
    },
    {
      "image": "https://phashion.moe/images/Eyebrows/Straight-Eyebrows.png",
      "title": "Straight Eyebrows",
      "category": "Eyebrows"
    },
    {
      "image": "https://phashion.moe/images/Eyelashes/Slit-Eyelashes-Set.png",
      "title": "Slit Eyelashes Set",
      "category": "Eyelashes"
    },
    {
      "image": "https://phashion.moe/images/Accessories/Just-Married-Cans.png",
      "title": "Just Married Cans",
      "category": "Accessories"
    },
    {
      "image": "https://phashion.moe/images/Accessories/X-Thrusters.png",
      "title": "X-Thrusters",
      "category": "Accessories"
    },
    {
      "image": "https://phashion.moe/images/Accessories/X-Thrusters-B.png",
      "title": "X-Thrusters B",
      "category": "Accessories"
    },
    {
      "image": "https://phashion.moe/images/Accessories/White-Flower-Wrist-R.png",
      "title": "White Flower Wrist R",
      "category": "Accessories"
    },
    {
      "image": "https://phashion.moe/images/Accessories/White-Flower-Wrist-L.png",
      "title": "White Flower Wrist L",
      "category": "Accessories"
    },
    {
      "image": "https://phashion.moe/images/Accessories/Black-Flower-Wrist-R.png",
      "title": "Black Flower Wrist R",
      "category": "Accessories"
    },
    {
      "image": "https://phashion.moe/images/Accessories/Black-Flower-Wrist-L.png",
      "title": "Black Flower Wrist L",
      "category": "Accessories"
    },
    {
      "image": "https://phashion.moe/images/Accessories/Rain-Cloud.png",
      "title": "Rain Cloud",
      "category": "Accessories"
    },
    {
      "image": "https://phashion.moe/images/Accessories/Rainbow.png",
      "title": "Rainbow",
      "category": "Accessories"
    },
    {
      "image": "https://phashion.moe/images/Accessories/Umbrella-Black.png",
      "title": "Umbrella: Black",
      "category": "Accessories"
    },
    {
      "image": "https://phashion.moe/images/Accessories/Umbrella-Red.png",
      "title": "Umbrella: Red",
      "category": "Accessories"
    },
    {
      "image": "https://phashion.moe/images/Accessories/Umbrella-Blue.png",
      "title": "Umbrella: Blue",
      "category": "Accessories"
    },
    {
      "image": "https://phashion.moe/images/Accessories/Clear-Skies-Charm.png",
      "title": "Clear Skies Charm",
      "category": "Accessories"
    },
    {
      "image": "https://phashion.moe/images/Accessories/Kappa-Head-Dish.png",
      "title": "Kappa Head Dish",
      "category": "Accessories"
    },
    {
      "image": "https://phashion.moe/images/Stickers/Diva-Sticker-Set.png",
      "title": "Diva Sticker Set",
      "category": "Stickers"
    },
    {
      "image": "https://phashion.moe/images/Stickers/Nozze-Sticker-Set.png",
      "title": "Nozze Sticker Set",
      "category": "Stickers"
    },
    {
      "image": "https://phashion.moe/images/Stickers/Cathedral-Sticker-Set.png",
      "title": "Cathedral Sticker Set",
      "category": "Stickers"
    },
    {
      "image": "https://phashion.moe/images/Stickers/Excellence-Sticker-Set.png",
      "title": "Excellence Sticker Set",
      "category": "Stickers"
    },
    {
      "image": "https://phashion.moe/images/Stickers/Elegance-Sticker-Set.png",
      "title": "Elegance Sticker Set",
      "category": "Stickers"
    }
  ]
}