{
  "type": "AC Scratch Ticket",
  "sourceUrl": "https://pso2.com/news/scratch-tickets/segalegacy",
  "title": "Sega Legacy",
  "slug": "Collections/AC-Scratch-Ticket/segalegacy",
  "items": [
    {
      "title": "Akira Replica",
      "category": "Outfit",
      "slug": "Outfit/Akira-Replica"
    },
    {
      "title": "Shinsengumi Chief Robe M",
      "category": "Outfit",
      "slug": "Outfit/Shinsengumi-Chief-Robe-M"
    },
    {
      "title": "Goro Majima Style",
      "category": "Outfit",
      "slug": "Outfit/Goro-Majima-Style"
    },
    {
      "title": "Alicia Replica",
      "category": "Outfit",
      "slug": "Outfit/Alicia-Replica"
    },
    {
      "title": "Selvaria Replica",
      "category": "Outfit",
      "slug": "Outfit/Selvaria-Replica"
    },
    {
      "title": "Selvaria Swimwear",
      "category": "Outfit",
      "slug": "Outfit/Selvaria-Swimwear"
    },
    {
      "title": "Selvaria Zwei",
      "category": "Outfit",
      "slug": "Outfit/Selvaria-Zwei"
    },
    {
      "title": "Arle Replica",
      "category": "Outfit",
      "slug": "Outfit/Arle-Replica"
    },
    {
      "title": "Student Style Replica",
      "category": "Outfit",
      "slug": "Outfit/Student-Style-Replica"
    },
    {
      "title": "Shinsengumi Chief Robe F",
      "category": "Outfit",
      "slug": "Outfit/Shinsengumi-Chief-Robe-F"
    },
    {
      "title": "Riley Replica",
      "category": "Outerwear",
      "slug": "Outerwear/Riley-Replica"
    },
    {
      "title": "Kai Schulen Replica",
      "category": "Outerwear",
      "slug": "Outerwear/Kai-Schulen-Replica"
    },
    {
      "title": "Crymaria Replica",
      "category": "Outerwear",
      "slug": "Outerwear/Crymaria-Replica"
    },
    {
      "title": "Riley Replica",
      "category": "Basewear",
      "slug": "Basewear/Riley-Replica"
    },
    {
      "title": "Kai Schulen Replica",
      "category": "Basewear",
      "slug": "Basewear/Kai-Schulen-Replica"
    },
    {
      "title": "Crymaria Replica",
      "category": "Basewear",
      "slug": "Basewear/Crymaria-Replica"
    },
    {
      "title": "Akira Hair",
      "category": "Hairstyle",
      "slug": "Hairstyle/Akira-Hair"
    },
    {
      "title": "Saito Hajime Topknot",
      "category": "Hairstyle",
      "slug": "Hairstyle/Saito-Hajime-Topknot"
    },
    {
      "title": "Goro Majima Hairstyle",
      "category": "Hairstyle",
      "slug": "Hairstyle/Goro-Majima-Hairstyle"
    },
    {
      "title": "Selvaria Long Hair",
      "category": "Hairstyle",
      "slug": "Hairstyle/Selvaria-Long-Hair"
    },
    {
      "title": "Arle Half-Up",
      "category": "Hairstyle",
      "slug": "Hairstyle/Arle-Half-Up"
    },
    {
      "title": "Student Style Hair",
      "category": "Hairstyle",
      "slug": "Hairstyle/Student-Style-Hair"
    },
    {
      "title": "Alicia Pigtails",
      "category": "Hairstyle",
      "slug": "Hairstyle/Alicia-Pigtails"
    },
    {
      "title": "Alicia Bandana",
      "category": "Hairstyle",
      "slug": "Hairstyle/Alicia-Bandana"
    },
    {
      "title": "Riley Hair",
      "category": "Hairstyle",
      "slug": "Hairstyle/Riley-Hair"
    },
    {
      "title": "Kai Schulen Hair 1",
      "category": "Hairstyle",
      "slug": "Hairstyle/Kai-Schulen-Hair-1"
    },
    {
      "title": "Kai Schulen Hair 2",
      "category": "Hairstyle",
      "slug": "Hairstyle/Kai-Schulen-Hair-2"
    },
    {
      "title": "Crymaria Hair",
      "category": "Hairstyle",
      "slug": "Hairstyle/Crymaria-Hair"
    },
    {
      "title": "Narrow Highlighted Eyes (L)",
      "category": "Eyes",
      "slug": "Eyes/Narrow-Highlighted-Eyes-L"
    },
    {
      "title": "Narrow Highlighted Eyes (S)",
      "category": "Eyes",
      "slug": "Eyes/Narrow-Highlighted-Eyes-S"
    },
    {
      "title": "Color Contacts (L)",
      "category": "Eyes",
      "slug": "Eyes/Color-Contacts-L"
    },
    {
      "title": "Color Contacts (S)",
      "category": "Eyes",
      "slug": "Eyes/Color-Contacts-S"
    },
    {
      "title": "Transparent Pupils",
      "category": "Eyes",
      "slug": "Eyes/Transparent-Pupils"
    },
    {
      "title": "Goro Majima Facial Hair",
      "category": "Facepaint",
      "slug": "Facepaint/Goro-Majima-Facial-Hair"
    },
    {
      "title": "Riley’s Tights",
      "category": "Body Paint",
      "slug": "Body-Paint/Riley-s-Tights"
    },
    {
      "title": "Goro Majima Eyepatch",
      "category": "Accessory",
      "slug": "Accessory/Goro-Majima-Eyepatch"
    },
    {
      "title": "Red Puyo Hat",
      "category": "Accessory",
      "slug": "Accessory/Red-Puyo-Hat"
    },
    {
      "title": "Carbuncle Pochette",
      "category": "Accessory",
      "slug": "Accessory/Carbuncle-Pochette"
    },
    {
      "title": "Riley’s Hairband",
      "category": "Accessory",
      "slug": "Accessory/Riley-s-Hairband"
    },
    {
      "title": "Riley’s Artillery",
      "category": "Accessory",
      "slug": "Accessory/Riley-s-Artillery"
    },
    {
      "title": "Kai Schulen Hat",
      "category": "Accessory",
      "slug": "Accessory/Kai-Schulen-Hat"
    },
    {
      "title": "Crymaria Hat",
      "category": "Accessory",
      "slug": "Accessory/Crymaria-Hat"
    },
    {
      "title": "Segmented Wing L",
      "category": "Accessory",
      "slug": "Accessory/Segmented-Wing-L"
    },
    {
      "title": "Segmented Wing R",
      "category": "Accessory",
      "slug": "Accessory/Segmented-Wing-R"
    },
    {
      "title": "Side Extensions",
      "category": "Accessory",
      "slug": "Accessory/Side-Extensions"
    },
    {
      "title": "Colored Side Extensions: Black",
      "category": "Accessory",
      "slug": "Accessory/Colored-Side-Extensions-Black"
    },
    {
      "title": "Colored Side Extensions: Blue",
      "category": "Accessory",
      "slug": "Accessory/Colored-Side-Extensions-Blue"
    },
    {
      "title": "Colored Side Extensions: Purple",
      "category": "Accessory",
      "slug": "Accessory/Colored-Side-Extensions-Purple"
    },
    {
      "title": "Colored Side Extensions: White",
      "category": "Accessory",
      "slug": "Accessory/Colored-Side-Extensions-White"
    },
    {
      "title": "Colored Side Extensions: Yellow",
      "category": "Accessory",
      "slug": "Accessory/Colored-Side-Extensions-Yellow"
    },
    {
      "title": "Colored Side Extensions: Red",
      "category": "Accessory",
      "slug": "Accessory/Colored-Side-Extensions-Red"
    },
    {
      "title": "Long Ribbon A",
      "category": "Accessory",
      "slug": "Accessory/Long-Ribbon-A"
    },
    {
      "title": "Long Ribbon B",
      "category": "Accessory",
      "slug": "Accessory/Long-Ribbon-B"
    },
    {
      "title": "Squad E Emblem",
      "category": "Sticker",
      "slug": "Sticker/Squad-E-Emblem"
    },
    {
      "title": "Zechs Owl Emblem",
      "category": "Sticker",
      "slug": "Sticker/Zechs-Owl-Emblem"
    },
    {
      "title": "Goro Majima Bat",
      "category": "Weapon",
      "slug": "Weapon/Goro-Majima-Bat"
    },
    {
      "title": "Goro Majima Strike",
      "category": "Weapon",
      "slug": "Weapon/Goro-Majima-Strike"
    },
    {
      "title": "Kai Schulen Sniper Rifle",
      "category": "Weapon",
      "slug": "Weapon/Kai-Schulen-Sniper-Rifle"
    },
    {
      "title": "Valkyria’s Lance",
      "category": "Weapon",
      "slug": "Weapon/Valkyria-s-Lance"
    },
    {
      "title": "Valkyria’s Staff",
      "category": "Weapon",
      "slug": "Weapon/Valkyria-s-Staff"
    }
  ]
}