{
  "image": "https://phashion.moe/images/Outerwear/Occultic-Vixen.png",
  "title": "Occultic Vixen",
  "gender": {
    "female": true,
    "male": false
  },
  "race": {
    "humanoid": true,
    "cast": true
  },
  "category": "Outerwear",
  "collection": {
    "id": "silkendreams",
    "type": "AC Scratch Ticket",
    "sourceUrl": "https://pso2.com/news/scratch-tickets/silkendreams",
    "title": "Silken Dreams",
    "image": "https://phashion.moe/images/Collections/AC-Scratch-Ticket/silkendreams.jpg"
  },
  "tradeable": true
}